qiskit/providers/honeywell/VERSION.txt
qiskit/providers/honeywell/__init__.py
qiskit/providers/honeywell/apiconstants.py
qiskit/providers/honeywell/exceptions.py
qiskit/providers/honeywell/honeywellbackend.py
qiskit/providers/honeywell/honeywelljob.py
qiskit/providers/honeywell/honeywellprovider.py
qiskit/providers/honeywell/version.py
qiskit/providers/honeywell/api/__init__.py
qiskit/providers/honeywell/api/exceptions.py
qiskit/providers/honeywell/api/honeywellclient.py
qiskit/providers/honeywell/api/session.py
qiskit/providers/honeywell/api/rest/__init__.py
qiskit/providers/honeywell/api/rest/backend.py
qiskit/providers/honeywell/api/rest/base.py
qiskit/providers/honeywell/api/rest/job.py
qiskit/providers/honeywell/api/rest/root.py
qiskit/providers/honeywell/credentials/__init__.py
qiskit/providers/honeywell/credentials/credentials.py
qiskit_honeywell_provider-0.2.1.dist-info/LICENSE.txt
qiskit_honeywell_provider-0.2.1.dist-info/METADATA
qiskit_honeywell_provider-0.2.1.dist-info/WHEEL
qiskit_honeywell_provider-0.2.1.dist-info/top_level.txt
qiskit_honeywell_provider-0.2.1.dist-info/RECORD
