Metadata-Version: 2.1
Name: qiskit-honeywell-provider
Version: 0.2.1
Summary: Qiskit provider for accessing the quantum devices at Honeywell
Home-page: https://github.com/qiskit-community/qiskit-honeywell-provider
Author: Honeywell
Author-email: dominic.lucchetti@honeywell.com
License: Apache 2.0
Project-URL: Bug Tracker, https://github.com/qiskit-community/qiskit-honeywell-provider/issues
Project-URL: Documentation, https://qiskit.org/documentation/
Project-URL: Source Code, https://github.com/qiskit-community/qiskit-honeywell-provider
Keywords: qiskit quantum
Classifier: License :: OSI Approved :: Apache Software License
Classifier: Intended Audience :: Developers
Classifier: Intended Audience :: Science/Research
Classifier: Operating System :: OS Independent
Classifier: Operating System :: Microsoft :: Windows
Classifier: Operating System :: MacOS
Classifier: Operating System :: POSIX :: Linux
Classifier: Programming Language :: Python :: 3 :: Only
Classifier: Programming Language :: Python :: 3.6
Classifier: Programming Language :: Python :: 3.7
Classifier: Programming Language :: Python :: 3.8
Classifier: Programming Language :: Python :: 3.9
Classifier: Topic :: Scientific/Engineering
Requires-Python: >=3.6
License-File: LICENSE.txt
Requires-Dist: nest-asyncio (>=1.2.0)
Requires-Dist: qiskit-terra (>=0.16.0)
Requires-Dist: requests (>=2.19)
Requires-Dist: websockets (>=7)
Requires-Dist: pyjwt (<2,>=1.7.1)
Requires-Dist: keyring (>=10.6.0)
